{
  "$schema": "http://json-schema.org/draft-07/schema#",
  "$id": "hexa-bio/_python_bridge/spec/ribotac_v1.schema.json",
  "title": "ribotac_v1 — RIBOTAC sub-axis output rows",
  "description": "Output schema for _python_bridge/module/ribotac_sim.py. One row per RIBOnuclease-TArgeting Chimera: the mass-action ternary-complex occupancy of Target.R.RNase-L and the catalytic multiple-turnover advantage over a stoichiometric RNA binder. RIBOTAC is a SUB-AXIS :> BIFUNCTIONAL (expansion-main, AXIS/HIERARCHY.tape) — NOT a hexa-bio core-5 axis; it has a soft cross-dependence ?> RIBOZYME (core, shared multiple-turnover RNA cleavage). In-silico simulator-consistency only; RIBOTAC is research-stage (AGENTS.tape g8/f2).",
  "type": "object",
  "required": ["schema", "ribotac", "binary_fraction", "ternary_fraction", "turnover_number", "is_catalytic", "effective_rna_neutralized_per_molecule"],
  "properties": {
    "schema": {
      "type": "string",
      "const": "ribotac_v1"
    },
    "ribotac": {
      "type": "string",
      "description": "RIBOTAC identifier within the deterministic panel (or the stoichiometric reference)."
    },
    "drug_precedent": {
      "type": "string",
      "description": "Own modality precedent (g3/f1 — described by precedent, never lattice-derived)."
    },
    "modality_stage": {
      "type": "string",
      "description": "Development stage of the modality; RIBOTAC is research-stage (no approved RIBOTAC)."
    },
    "conc_target_nM": {
      "type": "number",
      "exclusiveMinimum": 0,
      "description": "Assay concentration of the structured RNA target (nM)."
    },
    "conc_ribotac_nM": {
      "type": "number",
      "exclusiveMinimum": 0,
      "description": "Assay concentration of the bifunctional RIBOTAC molecule (nM)."
    },
    "conc_rnase_nM": {
      "type": "number",
      "exclusiveMinimum": 0,
      "description": "Assay concentration of recruitable RNase-L (nM)."
    },
    "rna_length_nt": {
      "type": "integer",
      "minimum": 0,
      "description": "Length of the target RNA (nt)."
    },
    "dot_bracket": {
      "type": "string",
      "description": "Vienna dot-bracket secondary structure of the target RNA (parent RIBOZYME-axis Nussinov solver, imported)."
    },
    "num_base_pairs": {
      "type": "integer",
      "minimum": 0,
      "description": "Number of base pairs in the target RNA secondary structure."
    },
    "pair_density": {
      "type": "number",
      "minimum": 0,
      "description": "2*num_base_pairs/length — structuredness proxy for the RNA target."
    },
    "dot_bracket_balanced": {
      "type": "boolean",
      "description": "True iff the dot-bracket structure is balanced/nested."
    },
    "structured": {
      "type": "boolean",
      "description": "True iff the RNA target has at least one base pair (RIBOTAC needs a structured target)."
    },
    "k_d1_nM": {
      "type": "number",
      "exclusiveMinimum": 0,
      "description": "Dissociation constant of the RNA-binding warhead to the RNA target (nM)."
    },
    "k_d2_nM": {
      "type": "number",
      "exclusiveMinimum": 0,
      "description": "Intrinsic dissociation constant of the recruiter warhead to RNase-L (nM)."
    },
    "alpha": {
      "type": "number",
      "minimum": 1,
      "description": "Ternary cooperativity factor (>= 1); linker pre-pays the entropy of the second binding event."
    },
    "k_d2_effective_nM": {
      "type": "number",
      "exclusiveMinimum": 0,
      "description": "Effective second-site dissociation constant K_d2/alpha (nM)."
    },
    "binary_fraction": {
      "type": "number",
      "minimum": 0,
      "maximum": 1,
      "description": "Mass-action occupancy of the Target.R binary complex."
    },
    "rnase_site_fraction": {
      "type": "number",
      "minimum": 0,
      "maximum": 1,
      "description": "Mass-action occupancy of the RNase-L recruiter site, given the binary complex."
    },
    "ternary_fraction": {
      "type": "number",
      "minimum": 0,
      "maximum": 1,
      "description": "Mass-action fraction of RNA target in the Target.R.RNase ternary complex = binary_fraction*rnase_site_fraction."
    },
    "k_cat_per_s": {
      "type": "number",
      "exclusiveMinimum": 0,
      "description": "Recruited-RNase-L catalytic turnover rate for the bound RNA (1/s)."
    },
    "cycle_time_s": {
      "type": "number",
      "exclusiveMinimum": 0,
      "description": "Catalytic cycle time tau = 1/k_cat (s)."
    },
    "t_exposure_s": {
      "type": "number",
      "exclusiveMinimum": 0,
      "description": "Exposure window over which turnovers accumulate (s)."
    },
    "turnover_number": {
      "type": "number",
      "minimum": 0,
      "description": "RNA copies neutralized per molecule = k_cat*t_exposure (1 for the stoichiometric reference)."
    },
    "stoichiometric_turnover": {
      "type": "number",
      "description": "Single-turnover reference value (1.0) — a stoichiometric binder neutralizes 1 RNA per molecule."
    },
    "catalytic_advantage_over_stoichiometric": {
      "type": "number",
      "minimum": 0,
      "description": "Turnover number divided by the stoichiometric reference (the catalytic advantage)."
    },
    "is_catalytic": {
      "type": "boolean",
      "description": "True iff turnover_number > 1 (a genuine multiple-turnover catalyst)."
    },
    "effective_rna_neutralized_per_molecule": {
      "type": "number",
      "minimum": 0,
      "description": "Ternary-fraction-weighted RNA copies neutralized per molecule."
    }
  },
  "additionalProperties": true
}
